butterflask/Widget.py
butterflask/__init__.py
butterflask/class_formatter.py
butterflask/js_code_generator.py
butterflask/style_formatter.py
butterflask/Widgets/Button.py
butterflask/Widgets/Column.py
butterflask/Widgets/Image.py
butterflask/Widgets/Row.py
butterflask/Widgets/Text.py
butterflask/Widgets/__init__.py
butterflask-1.0.0.dist-info/LICENSE
butterflask-1.0.0.dist-info/METADATA
butterflask-1.0.0.dist-info/WHEEL
butterflask-1.0.0.dist-info/top_level.txt
butterflask-1.0.0.dist-info/RECORD
