Metadata-Version: 2.1
Name: butterflask
Version: 1.0.0
Summary: A modern lightweight Python framework to create highly responsible front-end code on the fly
Home-page: https://github.com/Shubhgajj2004/ButterFlaskUI
Author: Shubh Gajjar
Author-email: shubhgajjar2004@gmail.com
License: UNKNOWN
Platform: UNKNOWN
Classifier: Intended Audience :: Developers
Classifier: License :: OSI Approved :: MIT License
Classifier: Programming Language :: Python :: 3
Classifier: Programming Language :: Python :: 3.10
License-File: LICENSE
